[
{"srctrue":"https://gp0809.github.io/createT/images/true1.png","srcfalse":"https://gp0809.github.io/createT/images/false1.png"},
{"srctrue":"https://gp0809.github.io/createT/images/true2.jpg","srcfalse":"https://gp0809.github.io/createT/images/false2.jpg"},
{"srctrue":"https://gp0809.github.io/createT/images/true3.jpg","srcfalse":"https://gp0809.github.io/createT/images/false3.jpg"},
{"srctrue":"https://gp0809.github.io/createT/images/true4.jpg","srcfalse":"https://gp0809.github.io/createT/images/false4.jpg"},
{"srctrue":"https://gp0809.github.io/createT/images/true5.jpg","srcfalse":"https://gp0809.github.io/createT/images/false5.jpg"},
{"srctrue":"https://gp0809.github.io/createT/images/true6.jpg","srcfalse":"https://gp0809.github.io/createT/images/false6.jpg"},
{"srctrue":"https://gp0809.github.io/createT/images/true7.jpg","srcfalse":"https://gp0809.github.io/createT/images/false7.jpg"},
{"srctrue":"https://gp0809.github.io/createT/images/true8.jpg","srcfalse":"https://gp0809.github.io/createT/images/false8.jpg"},
{"srctrue":"https://gp0809.github.io/createT/images/true9.jpg","srcfalse":"https://gp0809.github.io/createT/images/false9.jpg"},
{"srctrue":"https://gp0809.github.io/createT/images/true10.jpg","srcfalse":"https://gp0809.github.io/createT/images/false10.jpg"},
{"srctrue":"https://gp0809.github.io/createT/images/true11.jpg","srcfalse":"https://gp0809.github.io/createT/images/false11.jpg"},
{"srctrue":"https://gp0809.github.io/createT/images/true12.jpg","srcfalse":"https://gp0809.github.io/createT/images/false12.jpg"},
{"srctrue":"https://gp0809.github.io/createT/images/true13.jpg","srcfalse":"https://gp0809.github.io/createT/images/false13.jpg"},
{"srctrue":"https://gp0809.github.io/createT/images/true14.jpg","srcfalse":"https://gp0809.github.io/createT/images/false14.jpg"},
{"srctrue":"https://gp0809.github.io/createT/images/true15.jpg","srcfalse":"https://gp0809.github.io/createT/images/false15.jpg"},
{"srctrue":"https://gp0809.github.io/createT/images/true16.jpg","srcfalse":"https://gp0809.github.io/createT/images/false16.jpg"}
]  		 